pyserini_indexer-0.3.1.dist-info/METADATA
pyserini_indexer-0.3.1.dist-info/WHEEL
pyserini_indexer-0.3.1.dist-info/entry_points.txt
pyserini_indexer/__init__.py
pyserini_indexer/__main__.py
pyserini_indexer/handlers/__init__.py
pyserini_indexer/handlers/indexes.py
pyserini_indexer/handlers/searcher.py
pyserini_indexer/utils/__init__.py
pyserini_indexer/utils/models.py
pyserini_indexer/utils/splitter.py
pyserini_indexer/utils/vectors.py
pyserini_indexer-0.3.1.dist-info/RECORD
