Metadata-Version: 2.1
Name: pyserini-indexer
Version: 0.3.1
Summary: Helper application for building search indexes with pyserini
Author-Email: michal <michalwilk139@gmail.com>
License: MIT
Requires-Python: >=3.9
Requires-Dist: pyserini>=0.21.0
Requires-Dist: faiss-cpu>=1.7.4
Requires-Dist: torch>=2.0.1
